[{"name":"Food","funding":0,"current_requirement":598000000},{"name":"Nutrition","funding":0,"current_requirement":105600000},{"name":"Health","funding":0,"current_requirement":42800000},{"name":"WASH","funding":0,"current_requirement":86450296},{"name":"Agriculture","funding":0,"current_requirement":41900000},{"name":"Education","funding":0,"current_requirement":45504400},{"name":"Protection","funding":0,"current_requirement":11100000},{"name":"Emergency Shelter/NFI","funding":0,"current_requirement":17280000}]